canfar/__init__.py
canfar/client.py
canfar/context.py
canfar/images.py
canfar/overview.py
canfar/sessions.py
canfar/auth/__init__.py
canfar/auth/oidc.py
canfar/auth/x509.py
canfar/cli/__init__.py
canfar/cli/alias.py
canfar/cli/auth.py
canfar/cli/config.py
canfar/cli/create.py
canfar/cli/delete.py
canfar/cli/events.py
canfar/cli/image.py
canfar/cli/info.py
canfar/cli/logs.py
canfar/cli/main.py
canfar/cli/open.py
canfar/cli/prune.py
canfar/cli/ps.py
canfar/cli/run.py
canfar/cli/stats.py
canfar/cli/version.py
canfar/exceptions/__init__.py
canfar/exceptions/context.py
canfar/helpers/__init__.py
canfar/helpers/distributed.py
canfar/hooks/__init__.py
canfar/hooks/httpx/__init__.py
canfar/hooks/httpx/auth.py
canfar/hooks/httpx/errors.py
canfar/hooks/httpx/expiry.py
canfar/hooks/typer/__init__.py
canfar/hooks/typer/aliases.py
canfar/models/__init__.py
canfar/models/auth.py
canfar/models/config.py
canfar/models/http.py
canfar/models/registry.py
canfar/models/session.py
canfar/models/types.py
canfar/utils/__init__.py
canfar/utils/build.py
canfar/utils/console.py
canfar/utils/convert.py
canfar/utils/discover.py
canfar/utils/display.py
canfar/utils/funny.py
canfar/utils/garble.py
canfar/utils/jwt.py
canfar/utils/logging.py
canfar/utils/vosi.py
canfar-1.2.0.dist-info/METADATA
canfar-1.2.0.dist-info/WHEEL
canfar-1.2.0.dist-info/entry_points.txt
canfar-1.2.0.dist-info/licenses/LICENSE
canfar-1.2.0.dist-info/RECORD
