Metadata-Version: 2.4
Name: canfar
Version: 1.2.0
Summary: Python Client for CANFAR Science Platform
Project-URL: Homepage, https://opencadc.github.io/canfar/
Project-URL: Repository, https://github.com/opencadc/canfar
Project-URL: Documentation, https://opencadc.github.io/canfar/
Project-URL: Changelog, https://opencadc.github.io/canfar/changelog/
Project-URL: Issues, https://github.com/opencadc/canfar/issues
Author-email: Shiny Brar <shiny.brar@nrc-cnrc.gc.ca>
Maintainer-email: Shiny Brar <shiny.brar@nrc-cnrc.gc.ca>
License:                     GNU AFFERO GENERAL PUBLIC LICENSE
License-File: LICENSE
Keywords: api,canfar,client,container,platform,python
Classifier: Development Status :: 4 - Beta
Classifier: Environment :: Console
Classifier: Intended Audience :: Developers
Classifier: Intended Audience :: Education
Classifier: Intended Audience :: Science/Research
Classifier: Intended Audience :: System Administrators
Classifier: License :: OSI Approved :: GNU Affero General Public License v3 or later (AGPLv3+)
Classifier: Natural Language :: English
Classifier: Operating System :: MacOS :: MacOS X
Classifier: Operating System :: POSIX :: Linux
Classifier: Programming Language :: Python :: 3 :: Only
Classifier: Programming Language :: Python :: 3.10
Classifier: Programming Language :: Python :: 3.11
Classifier: Programming Language :: Python :: 3.12
Classifier: Programming Language :: Python :: 3.13
Classifier: Programming Language :: Python :: Implementation :: CPython
Classifier: Topic :: Internet :: WWW/HTTP :: HTTP Servers
Classifier: Topic :: Scientific/Engineering :: Astronomy
Classifier: Topic :: Scientific/Engineering :: Physics
Classifier: Topic :: Software Development :: Libraries :: Python Modules
Requires-Python: >=3.10
Requires-Dist: cadcutils>=1.5.4
Requires-Dist: defusedxml>=0.7.1
Requires-Dist: httpx[http2]>=0.28.1
Requires-Dist: humanize>=4.12.3
Requires-Dist: pydantic-settings>=2.9.1
Requires-Dist: pydantic>=2.9.2
Requires-Dist: pyyaml>=6.0.2
Requires-Dist: questionary>=2.1.0
Requires-Dist: rich>=13.9.4
Requires-Dist: segno>=1.6.6
Requires-Dist: toml>=0.10.2
Requires-Dist: typer>=0.16.0
